mygpio.py
mygpio-1.0.1.dist-info/LICENSE
mygpio-1.0.1.dist-info/METADATA
mygpio-1.0.1.dist-info/WHEEL
mygpio-1.0.1.dist-info/top_level.txt
mygpio-1.0.1.dist-info/RECORD
