Metadata-Version: 2.1
Name: mygpio
Version: 1.0.1
Summary: GPIO Library which extends GPIO functions
Home-page: https://github.com/governorbaloyi/pypi-mygpio
Author: Governor Baloyi
Author-email: governor.baloyi@gmail.com
License: UNKNOWN
Platform: UNKNOWN
Classifier: Development Status :: 1 - Planning
Classifier: Framework :: Pytest
Classifier: License :: OSI Approved :: MIT License
Classifier: Programming Language :: Python :: 3 :: Only
Requires-Dist: RPi.GPIO
Provides-Extra: dev
Requires-Dist: pytest (>=3.7) ; extra == 'dev'
